{"status":{"success":true,"httpstatuscode":301},"statistics":{"pagetitle":"Just a moment...","pageurl":"https://www.agerpres.ro/","time":8.27,"creditsremaining":933,"AIMscore":9.1,"allitemcount":6,"totalelements":45,"waveurl":"http://wave.webaim.org/report?url=https://www.agerpres.ro/"},"categories":{"error":{"description":"Errors","count":1},"contrast":{"description":"Contrast Errors","count":0},"alert":{"description":"Alerts","count":1},"feature":{"description":"Features","count":1},"structure":{"description":"Structural Elements","count":3},"aria":{"description":"ARIA","count":0}},"timestamp":1763393152934}